trytond/modules/health_surgery/COPYING
trytond/modules/health_surgery/README.rst
trytond/modules/health_surgery/__init__.py
trytond/modules/health_surgery/data/gnuhealth_commands.xml
trytond/modules/health_surgery/data/health_surgery_sequence.xml
trytond/modules/health_surgery/data/messages/messages.xml
trytond/modules/health_surgery/data/surgery_protocols.xml
trytond/modules/health_surgery/exceptions.py
trytond/modules/health_surgery/health.py
trytond/modules/health_surgery/health_surgery.py
trytond/modules/health_surgery/health_surgery_report.xml
trytond/modules/health_surgery/health_surgery_view.xml
trytond/modules/health_surgery/icons/surgery.svg
trytond/modules/health_surgery/locale/ar.po
trytond/modules/health_surgery/locale/de.po
trytond/modules/health_surgery/locale/el.po
trytond/modules/health_surgery/locale/eo.po
trytond/modules/health_surgery/locale/es.po
trytond/modules/health_surgery/locale/fr.po
trytond/modules/health_surgery/locale/health_surgery.pot
trytond/modules/health_surgery/locale/it_IT.po
trytond/modules/health_surgery/locale/ja_JP.po
trytond/modules/health_surgery/locale/ka.po
trytond/modules/health_surgery/locale/lo.po
trytond/modules/health_surgery/locale/pt_BR.po
trytond/modules/health_surgery/locale/sv.po
trytond/modules/health_surgery/locale/tr.po
trytond/modules/health_surgery/locale/uk.po
trytond/modules/health_surgery/locale/vi.po
trytond/modules/health_surgery/locale/zh_CN.po
trytond/modules/health_surgery/pyproject.toml
trytond/modules/health_surgery/report/__init__.py
trytond/modules/health_surgery/report/preoperative_assessment_report.fodt
trytond/modules/health_surgery/report/surgery_outpatient_report.fodt
trytond/modules/health_surgery/report/surgery_report.fodt
trytond/modules/health_surgery/report/surgery_report.py
trytond/modules/health_surgery/security/access_rights.xml
trytond/modules/health_surgery/sequences.py
trytond/modules/health_surgery/tests/__init__.py
trytond/modules/health_surgery/tests/test_health_surgery.py
gnuhealth_surgery-5.0.2.dist-info/METADATA
gnuhealth_surgery-5.0.2.dist-info/WHEEL
gnuhealth_surgery-5.0.2.dist-info/licenses/COPYING
gnuhealth_surgery-5.0.2.dist-info/RECORD
